gpyts/__init__.py
gpyts/asyncGpyts/__init__.py
gpyts/config/__init__.py
gpyts/errors/__init__.py
gpyts/syncGpyts/__init__.py
gpyts/types/__init__.py
Gpyts-1.0.3.dist-info/LICENSE
Gpyts-1.0.3.dist-info/METADATA
Gpyts-1.0.3.dist-info/WHEEL
Gpyts-1.0.3.dist-info/top_level.txt
Gpyts-1.0.3.dist-info/RECORD
