Metadata-Version: 2.1
Name: Gpyts
Version: 1.0.3
Summary: Gpyts is a library for Google translation and gTTS using Google Translation API.
Home-page: https://github.com/Ripeey/Gpyts
Author: Ripe
Author-email: ripeey@protonmail.com
License: MIT
Classifier: Programming Language :: Python :: 3
Classifier: License :: OSI Approved :: MIT License
Classifier: Development Status :: 5 - Production/Stable
Classifier: Operating System :: OS Independent
Requires-Python: >=3.6
License-File: LICENSE
Requires-Dist: aiofiles
Requires-Dist: aiohttp
Requires-Dist: requests
